case_prov/__init__.py
case_prov/case_prov_check.py
case_prov/case_prov_dot.py
case_prov/case_prov_rdf.py
case_prov/py.typed
case_prov/queries/__init__.py
case_prov/queries/construct-Activity.sparql
case_prov/queries/construct-Agent.sparql
case_prov/queries/construct-Collection.sparql
case_prov/queries/construct-Entity.sparql
case_prov/queries/construct-Person.sparql
case_prov/queries/construct-SoftwareAgent.sparql
case_prov/queries/construct-actedOnBehalfOf.sparql
case_prov/queries/construct-used-nothing.sparql
case_prov/queries/construct-used.sparql
case_prov/queries/construct-wasAssociatedWith.sparql
case_prov/queries/construct-wasAttributedTo.sparql
case_prov/queries/construct-wasDerivedFrom-map.sparql
case_prov/queries/construct-wasDerivedFrom.sparql
case_prov/queries/construct-wasGeneratedBy.sparql
case_prov/queries/construct-wasInformedBy-map.sparql
case_prov/queries/construct-wasInformedBy.sparql
case_prov/shapes/__init__.py
case_prov/shapes/case-prov.ttl
case_prov/shapes/prov-shapes.ttl
case_prov-0.12.2.dist-info/licenses/LICENSE
case_prov-0.12.2.dist-info/licenses/THIRD_PARTY_LICENSES.md
case_prov-0.12.2.dist-info/METADATA
case_prov-0.12.2.dist-info/WHEEL
case_prov-0.12.2.dist-info/entry_points.txt
case_prov-0.12.2.dist-info/top_level.txt
case_prov-0.12.2.dist-info/RECORD
