Metadata-Version: 2.4
Name: case_prov
Version: 0.12.2
Summary: A mapping of CASE to W3C PROV
Home-page: https://github.com/casework/CASE-Implementation-PROV-O
Author: Alex Nelson
Author-email: alexander.nelson@nist.gov
Classifier: Development Status :: 4 - Beta
Classifier: License :: OSI Approved :: Apache Software License
Classifier: Operating System :: OS Independent
Classifier: Programming Language :: Python :: 3
Requires-Python: >=3.9
License-File: LICENSE
License-File: THIRD_PARTY_LICENSES.md
Requires-Dist: case_utils<0.17.0,>=0.16.0
Requires-Dist: prov
Requires-Dist: pydot<4.0.0
Requires-Dist: pyshacl<0.27.0
Provides-Extra: testing
Requires-Dist: case_utils[testing]; extra == "testing"
Dynamic: license-file
